markdowngiver/__init__.py
markdowngiver/__main__.py
markdowngiver/server.py
superdupers-0.2.0.dist-info/METADATA
superdupers-0.2.0.dist-info/WHEEL
superdupers-0.2.0.dist-info/top_level.txt
superdupers-0.2.0.dist-info/RECORD
